suntime/__init__.py
suntime/suntime.py
suntime-1.3.1.dist-info/LICENSE
suntime-1.3.1.dist-info/METADATA
suntime-1.3.1.dist-info/WHEEL
suntime-1.3.1.dist-info/top_level.txt
suntime-1.3.1.dist-info/RECORD
