Metadata-Version: 2.1
Name: suntime
Version: 1.3.1
Summary: Simple sunset and sunrise time calculation python library
Home-page: https://github.com/SatAgro/suntime
Author: Krzysztof Stopa
License: LGPLv3
License-File: LICENSE
Requires-Dist: python-dateutil
